examples/__init__.py
examples/arabic_sts/__init__.py
examples/arabic_sts/arabic_preprocess.py
examples/arabic_sts/draw.py
examples/arabic_sts/normalizer.py
examples/arabic_sts/reader.py
examples/arabic_sts/run_experiment.py
examples/arabic_sts/config/__init__.py
examples/arabic_sts/config/transformer_config.py
examples/stsbenchmark/__init__.py
examples/stsbenchmark/run_experiment.py
examples/stsbenchmark/config/__init__.py
examples/stsbenchmark/config/transformer_config.py
ststransformers/__init__.py
ststransformers/algo/__init__.py
ststransformers/algo/model_args.py
ststransformers/algo/transformer_model.py
ststransformers/algo/utils.py
ststransformers/losses/__init__.py
ststransformers/losses/dice_loss.py
ststransformers/losses/focal_loss.py
ststransformers/losses/loss_utils.py
ststransformers/losses/tversky_loss.py
ststransformers/models/__init__.py
ststransformers/models/albert_model.py
ststransformers/models/bert_model.py
ststransformers/models/camembert_model.py
ststransformers/models/distilbert_model.py
ststransformers/models/electra_model.py
ststransformers/models/flaubert_model.py
ststransformers/models/layoutlm_model.py
ststransformers/models/longformer_model.py
ststransformers/models/mmbt_model.py
ststransformers/models/mobilebert_model.py
ststransformers/models/roberta_model.py
ststransformers/models/xlm_model.py
ststransformers/models/xlm_roberta_model.py
ststransformers/models/xlnet_model.py
ststransformers/util/__init__.py
ststransformers/util/evaluation.py
ststransformers/util/normalizer.py
ststransformers-0.0.5.dist-info/LICENSE
ststransformers-0.0.5.dist-info/METADATA
ststransformers-0.0.5.dist-info/WHEEL
ststransformers-0.0.5.dist-info/top_level.txt
ststransformers-0.0.5.dist-info/RECORD
