Metadata-Version: 2.1
Name: ststransformers
Version: 0.0.5
Summary: An easy-to-use wrapper library for using Transformers in Semantic Textual Similarity Tasks.
Home-page: https://github.com/TharinduDR/STS-Transformers
Author: Tharindu Ranasinghe
Author-email: rhtdranasinghe@gmail.com
License: UNKNOWN
Platform: UNKNOWN
Classifier: Intended Audience :: Science/Research
Classifier: License :: OSI Approved :: Apache Software License
Classifier: Programming Language :: Python :: 3
Classifier: Topic :: Scientific/Engineering :: Artificial Intelligence
Requires-Python: >=3.6
License-File: LICENSE
Requires-Dist: numpy
Requires-Dist: requests
Requires-Dist: tqdm (>=4.47.0)
Requires-Dist: regex
Requires-Dist: transformers (>=4.6.0)
Requires-Dist: datasets
Requires-Dist: scipy
Requires-Dist: scikit-learn
Requires-Dist: seqeval
Requires-Dist: tensorboard
Requires-Dist: tensorboardX
Requires-Dist: pandas
Requires-Dist: tokenizers
Requires-Dist: wandb (>=0.10.32)
Requires-Dist: sentencepiece
